multicons/__init__.py
multicons/consensus.py
multicons/core.py
multicons/utils.py
multicons-0.3.0.dist-info/LICENSE.md
multicons-0.3.0.dist-info/METADATA
multicons-0.3.0.dist-info/WHEEL
multicons-0.3.0.dist-info/top_level.txt
multicons-0.3.0.dist-info/zip-safe
multicons-0.3.0.dist-info/RECORD
