Metadata-Version: 2.1
Name: multicons
Version: 0.3.0
Summary: MultiCons (Multiple Consensuses) algorithm
Home-page: https://github.com/SergioSim/multicons
Author: SergioSim
Author-email: sergio.simonian@etu.univ-cotedazur.fr
License: MIT
Keywords: MultiCons,Multiple Consensuses,Consensus clustering
Classifier: Development Status :: 3 - Alpha
Classifier: Intended Audience :: Developers
Classifier: License :: OSI Approved :: MIT License
Classifier: Natural Language :: English
Classifier: Programming Language :: Python :: 3
Classifier: Programming Language :: Python :: 3.9
Classifier: Programming Language :: Python :: 3.10
Classifier: Programming Language :: Python :: 3.11
Classifier: Programming Language :: Python :: 3.12
Requires-Python: >=3.9
License-File: LICENSE.md
Requires-Dist: graphviz >=0.20
Requires-Dist: numpy >=1.24.0
Requires-Dist: pandas >=2.0.0
Requires-Dist: pyfim >=6.28
Requires-Dist: scikit-learn >=1.2.0
Provides-Extra: ci
Requires-Dist: twine ==5.0.0 ; extra == 'ci'
Provides-Extra: dev
Requires-Dist: bandit ==1.7.8 ; extra == 'dev'
Requires-Dist: black ==24.4.2 ; extra == 'dev'
Requires-Dist: flake8 ==7.0.0 ; extra == 'dev'
Requires-Dist: fuzzy-c-means ==1.7.2 ; extra == 'dev'
Requires-Dist: isort ==5.13.2 ; extra == 'dev'
Requires-Dist: jupyterlab ==4.1.8 ; extra == 'dev'
Requires-Dist: jupytext ==1.16.2 ; extra == 'dev'
Requires-Dist: kmedoids ==0.5.1 ; extra == 'dev'
Requires-Dist: matplotlib ==3.8.4 ; extra == 'dev'
Requires-Dist: mkdocs ==1.6.0 ; extra == 'dev'
Requires-Dist: mkdocs-jupyter ==0.24.7 ; extra == 'dev'
Requires-Dist: mkdocs-material ==9.5.21 ; extra == 'dev'
Requires-Dist: mkdocstrings[python] ==0.25.1 ; extra == 'dev'
Requires-Dist: pylint ==3.1.0 ; extra == 'dev'
Requires-Dist: pytest ==8.2.0 ; extra == 'dev'
Requires-Dist: pytest-cov ==5.0.0 ; extra == 'dev'
